{
    "interactionModel": {
        "languageModel": {
            "invocationName": "friendly events",
            "intents": [
                {
                    "name": "AMAZON.FallbackIntent",
                    "samples": []
                },
                {
                    "name": "AMAZON.CancelIntent",
                    "samples": [
                        "Quit",
                        "Exit",
                        "Stop",
                        "Cancel"
                    ]
                },
                {
                    "name": "AMAZON.HelpIntent",
                    "samples": [
                        "Help"
                    ]
                },
                {
                    "name": "AMAZON.StopIntent",
                    "samples": [
                        "Thank you",
                        "Thanks"
                    ]
                },
                {
                    "name": "AMAZON.NavigateHomeIntent",
                    "samples": []
                },
                {
                    "name": "CodegardenIntent",
                    "slots": [],
                    "samples": [
                        "next Codegarden",
                        "Codegarden",
                        "When is the most unique developer conference happening",
                        "How many days to Codegarden",
                        "When is the next Codegarden"
                    ]
                }
            ],
            "types": []
        }
    }
}